[{"in_reply_to_status_id_str":null,"in_reply_to_status_id":null,"supplemental_language":null,"created_at":"Mon May 14 10:09:45 +0000 2018","in_reply_to_user_id_str":null,"source":"<a href=\"http://instagram.com\" rel=\"nofollow\">Instagram</a>","possibly_sensitive_editable":true,"retweet_count":2,"retweeted":false,"geo":null,"in_reply_to_screen_name":null,"is_quote_status":false,"user_id_str":"14305560","full_text":"Wahai para penonton @StandUpIndo , gue punya pesan spesial untuk elo :) https://t.co/L19oFoSlMi","conversation_id":995969407867342849,"id_str":"995969407867342849","in_reply_to_user_id":null,"favorite_count":8,"id":995969407867342849,"place":null,"lang":"in","quote_count":1,"conversation_id_str":"995969407867342849","favorited":false,"possibly_sensitive":false,"coordinates":null,"truncated":false,"reply_count":3,"crawler_target":{"resource_type":"social_media","stream_type":"account","specific_resource_type":"twitter","target_name":"332919636","extra_content":"Standupindo"},"entities":{"hashtags":[],"symbols":[],"user_mentions":[{"screen_name":"Standupindo","name":"IG: standupindonesia","id":332919636,"id_str":"332919636","indices":[20,32]}],"urls":[{"url":"https://t.co/L19oFoSlMi","expanded_url":"https://www.instagram.com/p/BiwQRmSFrsL/?utm_source=ig_twitter_share","display_url":"instagram.com/p/BiwQRmSFrsL/…","indices":[72,95]}]},"user_id":14305560,"display_text_range":[0,95],"contributors":null,"user":{"id":14305560,"id_str":"14305560","name":"Pandji Pragiwaksono","screen_name":"pandji","location":"Indonesia","description":"Stand-Up Comedian with 8 Special who is now running COMIKA, a company devoted to create the world a funnier place.","url":"https://t.co/SEa8vNPYbA","entities":{"url":{"urls":[{"url":"https://t.co/SEa8vNPYbA","expanded_url":"https://linktr.ee/pandji.pragiwaksono","display_url":"linktr.ee/pandji.pragiwa…","indices":[0,23]}]},"description":{"urls":[]}},"protected":false,"followers_count":1572888,"fast_followers_count":0,"normal_followers_count":1572888,"friends_count":346,"listed_count":1566,"created_at":"Fri Apr 04 19:35:56 +0000 2008","favourites_count":2230,"utc_offset":null,"time_zone":null,"geo_enabled":true,"verified":true,"statuses_count":270177,"media_count":24117,"lang":null,"contributors_enabled":false,"is_translator":false,"is_translation_enabled":false,"profile_background_color":"000000","profile_background_image_url":"http://abs.twimg.com/images/themes/theme1/bg.png","profile_background_image_url_https":"https://abs.twimg.com/images/themes/theme1/bg.png","profile_background_tile":false,"profile_image_url":"http://pbs.twimg.com/profile_images/1341056153468354574/kcfQnHeI_normal.jpg","profile_image_url_https":"https://pbs.twimg.com/profile_images/1341056153468354574/kcfQnHeI_normal.jpg","profile_banner_url":"https://pbs.twimg.com/profile_banners/14305560/1608097720","profile_image_extensions_alt_text":null,"profile_image_extensions_media_availability":null,"profile_image_extensions_media_color":{"palette":[{"rgb":{"red":177,"green":184,"blue":190},"percentage":40.08},{"rgb":{"red":39,"green":47,"blue":35},"percentage":32.09},{"rgb":{"red":115,"green":114,"blue":97},"percentage":10},{"rgb":{"red":14,"green":42,"blue":56},"percentage":6.72},{"rgb":{"red":68,"green":75,"blue":34},"percentage":5.21}]},"profile_image_extensions":{"mediaStats":{"r":{"missing":null},"ttl":-1}},"profile_banner_extensions_alt_text":null,"profile_banner_extensions_media_availability":null,"profile_banner_extensions_media_color":{"palette":[{"rgb":{"red":162,"green":161,"blue":162},"percentage":76.76},{"rgb":{"red":38,"green":45,"blue":51},"percentage":19.59},{"rgb":{"red":213,"green":190,"blue":175},"percentage":0.18},{"rgb":{"red":44,"green":40,"blue":26},"percentage":0.16}]},"profile_banner_extensions":{"mediaStats":{"r":{"missing":null},"ttl":-1}},"profile_link_color":"3CB904","profile_sidebar_border_color":"164700","profile_sidebar_fill_color":"255211","profile_text_color":"979595","profile_use_background_image":true,"has_extended_profile":true,"default_profile":false,"default_profile_image":false,"pinned_tweet_ids":[],"pinned_tweet_ids_str":[],"has_custom_timelines":true,"can_dm":null,"following":null,"follow_request_sent":null,"notifications":null,"muting":null,"blocking":null,"blocked_by":null,"want_retweets":null,"advertiser_account_type":"promotable_user","advertiser_account_service_levels":["analytics"],"business_profile_state":"none","translator_type":"regular","withheld_in_countries":[],"followed_by":null,"ext":{"highlightedLabel":{"r":{"ok":{}},"ttl":-1}},"require_some_consent":false}},{"in_reply_to_status_id_str":null,"in_reply_to_status_id":null,"supplemental_language":null,"created_at":"Mon May 14 10:09:45 +0000 2018","in_reply_to_user_id_str":null,"source":"<a href=\"http://instagram.com\" rel=\"nofollow\">Instagram</a>","possibly_sensitive_editable":true,"retweet_count":2,"retweeted":false,"geo":null,"in_reply_to_screen_name":null,"is_quote_status":false,"user_id_str":"14305560","full_text":"Wahai para penonton @StandUpIndo , gue punya pesan spesial untuk elo :) https://t.co/L19oFoSlMi","conversation_id":995969407867342849,"id_str":"995969407867342849","in_reply_to_user_id":null,"favorite_count":8,"id":995969407867342849,"place":null,"lang":"in","quote_count":1,"conversation_id_str":"995969407867342849","favorited":false,"possibly_sensitive":false,"coordinates":null,"truncated":false,"reply_count":3,"crawler_target":{"resource_type":"social_media","stream_type":"account","specific_resource_type":"twitter","target_name":"332919636","extra_content":"Standupindo"},"entities":{"hashtags":[],"symbols":[],"user_mentions":[{"screen_name":"Standupindo","name":"IG: standupindonesia","id":332919636,"id_str":"332919636","indices":[20,32]}],"urls":[{"url":"https://t.co/L19oFoSlMi","expanded_url":"https://www.instagram.com/p/BiwQRmSFrsL/?utm_source=ig_twitter_share","display_url":"instagram.com/p/BiwQRmSFrsL/…","indices":[72,95]}]},"user_id":14305560,"display_text_range":[0,95],"contributors":null,"user":{"id":14305560,"id_str":"14305560","name":"Pandji Pragiwaksono","screen_name":"pandji","location":"Indonesia","description":"Stand-Up Comedian with 8 Special who is now running COMIKA, a company devoted to create the world a funnier place.","url":"https://t.co/SEa8vNPYbA","entities":{"url":{"urls":[{"url":"https://t.co/SEa8vNPYbA","expanded_url":"https://linktr.ee/pandji.pragiwaksono","display_url":"linktr.ee/pandji.pragiwa…","indices":[0,23]}]},"description":{"urls":[]}},"protected":false,"followers_count":1572888,"fast_followers_count":0,"normal_followers_count":1572888,"friends_count":346,"listed_count":1566,"created_at":"Fri Apr 04 19:35:56 +0000 2008","favourites_count":2230,"utc_offset":null,"time_zone":null,"geo_enabled":true,"verified":true,"statuses_count":270177,"media_count":24117,"lang":null,"contributors_enabled":false,"is_translator":false,"is_translation_enabled":false,"profile_background_color":"000000","profile_background_image_url":"http://abs.twimg.com/images/themes/theme1/bg.png","profile_background_image_url_https":"https://abs.twimg.com/images/themes/theme1/bg.png","profile_background_tile":false,"profile_image_url":"http://pbs.twimg.com/profile_images/1341056153468354574/kcfQnHeI_normal.jpg","profile_image_url_https":"https://pbs.twimg.com/profile_images/1341056153468354574/kcfQnHeI_normal.jpg","profile_banner_url":"https://pbs.twimg.com/profile_banners/14305560/1608097720","profile_image_extensions_alt_text":null,"profile_image_extensions_media_availability":null,"profile_image_extensions_media_color":{"palette":[{"rgb":{"red":177,"green":184,"blue":190},"percentage":40.08},{"rgb":{"red":39,"green":47,"blue":35},"percentage":32.09},{"rgb":{"red":115,"green":114,"blue":97},"percentage":10},{"rgb":{"red":14,"green":42,"blue":56},"percentage":6.72},{"rgb":{"red":68,"green":75,"blue":34},"percentage":5.21}]},"profile_image_extensions":{"mediaStats":{"r":{"missing":null},"ttl":-1}},"profile_banner_extensions_alt_text":null,"profile_banner_extensions_media_availability":null,"profile_banner_extensions_media_color":{"palette":[{"rgb":{"red":162,"green":161,"blue":162},"percentage":76.76},{"rgb":{"red":38,"green":45,"blue":51},"percentage":19.59},{"rgb":{"red":213,"green":190,"blue":175},"percentage":0.18},{"rgb":{"red":44,"green":40,"blue":26},"percentage":0.16}]},"profile_banner_extensions":{"mediaStats":{"r":{"missing":null},"ttl":-1}},"profile_link_color":"3CB904","profile_sidebar_border_color":"164700","profile_sidebar_fill_color":"255211","profile_text_color":"979595","profile_use_background_image":true,"has_extended_profile":true,"default_profile":false,"default_profile_image":false,"pinned_tweet_ids":[],"pinned_tweet_ids_str":[],"has_custom_timelines":true,"can_dm":null,"following":null,"follow_request_sent":null,"notifications":null,"muting":null,"blocking":null,"blocked_by":null,"want_retweets":null,"advertiser_account_type":"promotable_user","advertiser_account_service_levels":["analytics"],"business_profile_state":"none","translator_type":"regular","withheld_in_countries":[],"followed_by":null,"ext":{"highlightedLabel":{"r":{"ok":{}},"ttl":-1}},"require_some_consent":false}},{"in_reply_to_status_id_str":null,"in_reply_to_status_id":null,"supplemental_language":null,"created_at":"Mon May 14 11:52:39 +0000 2018","in_reply_to_user_id_str":null,"source":"<a href=\"http://twitter.com/download/android\" rel=\"nofollow\">Twitter for Android</a>","possibly_sensitive_editable":true,"quoted_status_id":995969407867342849,"retweet_count":0,"retweeted":false,"geo":null,"in_reply_to_screen_name":null,"is_quote_status":true,"user_id_str":"332919636","full_text":"Chek ig mimin dong, mantap mania~ https://t.co/kFr4GRSYyU","conversation_id":995995302053134336,"id_str":"995995302053134336","in_reply_to_user_id":null,"favorite_count":1,"id":995995302053134336,"place":null,"quoted_status_permalink":{"url":"https://t.co/kFr4GRSYyU","expanded":"https://twitter.com/pandji/status/995969407867342849","display":"twitter.com/pandji/status/…"},"lang":"in","quote_count":0,"conversation_id_str":"995995302053134336","favorited":false,"possibly_sensitive":false,"coordinates":null,"truncated":false,"reply_count":0,"crawler_target":{"resource_type":"social_media","stream_type":"account","specific_resource_type":"twitter","target_name":"332919636","extra_content":"Standupindo"},"entities":{"hashtags":[],"symbols":[],"user_mentions":[],"urls":[{"url":"https://t.co/kFr4GRSYyU","expanded_url":"https://twitter.com/pandji/status/995969407867342849","display_url":"twitter.com/pandji/status/…","indices":[34,57]}]},"user_id":332919636,"display_text_range":[0,33],"quoted_status_id_str":"995969407867342849","contributors":null,"user":{"id":332919636,"id_str":"332919636","name":"IG: standupindonesia","screen_name":"Standupindo","location":"Indonesia","description":"Rumah Komika Negeri\uD83C\uDDEE\uD83C\uDDE9 ——————————————————————— silakan intip @tokostandupindo","url":"https://t.co/65X2eZXZZg","entities":{"url":{"urls":[{"url":"https://t.co/65X2eZXZZg","expanded_url":"https://linktr.ee/Standupindo","display_url":"linktr.ee/Standupindo","indices":[0,23]}]},"description":{"urls":[]}},"protected":false,"followers_count":130219,"fast_followers_count":0,"normal_followers_count":130219,"friends_count":5,"listed_count":209,"created_at":"Sun Jul 10 17:21:07 +0000 2011","favourites_count":3,"utc_offset":null,"time_zone":null,"geo_enabled":true,"verified":false,"statuses_count":24590,"media_count":4064,"lang":null,"contributors_enabled":false,"is_translator":false,"is_translation_enabled":false,"profile_background_color":"C0DEED","profile_background_image_url":"http://abs.twimg.com/images/themes/theme1/bg.png","profile_background_image_url_https":"https://abs.twimg.com/images/themes/theme1/bg.png","profile_background_tile":false,"profile_image_url":"http://pbs.twimg.com/profile_images/1143894906449960960/04n4Tr1P_normal.jpg","profile_image_url_https":"https://pbs.twimg.com/profile_images/1143894906449960960/04n4Tr1P_normal.jpg","profile_banner_url":"https://pbs.twimg.com/profile_banners/332919636/1620923631","profile_image_extensions_alt_text":null,"profile_image_extensions_media_availability":null,"profile_image_extensions_media_color":{"palette":[{"rgb":{"red":255,"green":255,"blue":255},"percentage":80.49},{"rgb":{"red":10,"green":148,"blue":209},"percentage":6.87},{"rgb":{"red":218,"green":64,"blue":68},"percentage":3.9},{"rgb":{"red":226,"green":156,"blue":156},"percentage":3.19},{"rgb":{"red":149,"green":211,"blue":229},"percentage":2.73}]},"profile_image_extensions":{"mediaStats":{"r":{"missing":null},"ttl":-1}},"profile_banner_extensions_media_color":{"palette":[{"rgb":{"red":255,"green":255,"blue":255},"percentage":78},{"rgb":{"red":6,"green":6,"blue":6},"percentage":15.1},{"rgb":{"red":113,"green":113,"blue":114},"percentage":8.5}]},"profile_banner_extensions_alt_text":null,"profile_banner_extensions_media_availability":null,"profile_banner_extensions":{"mediaStats":{"r":{"missing":null},"ttl":-1}},"profile_link_color":"1DA1F2","profile_sidebar_border_color":"C0DEED","profile_sidebar_fill_color":"DDEEF6","profile_text_color":"333333","profile_use_background_image":true,"has_extended_profile":true,"default_profile":true,"default_profile_image":false,"pinned_tweet_ids":[1414791025025904642],"pinned_tweet_ids_str":["1414791025025904642"],"has_custom_timelines":false,"can_dm":null,"following":null,"follow_request_sent":null,"notifications":null,"muting":null,"blocking":null,"blocked_by":null,"want_retweets":null,"advertiser_account_type":"promotable_user","advertiser_account_service_levels":["analytics"],"business_profile_state":"none","translator_type":"none","withheld_in_countries":[],"followed_by":null,"ext":{"highlightedLabel":{"r":{"ok":{}},"ttl":-1}},"require_some_consent":false}},{"in_reply_to_status_id_str":"995969407867342849","in_reply_to_status_id":995969407867342849,"supplemental_language":null,"created_at":"Mon May 14 17:45:40 +0000 2018","in_reply_to_user_id_str":"14305560","source":"<a href=\"http://twitter.com/download/android\" rel=\"nofollow\">Twitter for Android</a>","retweet_count":0,"retweeted":false,"geo":null,"in_reply_to_screen_name":"pandji","is_quote_status":false,"user_id_str":"282551666","full_text":"@pandji @StandUpIndo bang ko gue kurang srek ya nongton suci 8?","conversation_id":995969407867342849,"id_str":"996084140918300672","in_reply_to_user_id":14305560,"favorite_count":0,"id":996084140918300672,"place":null,"lang":"in","quote_count":0,"conversation_id_str":"995969407867342849","favorited":false,"coordinates":null,"truncated":false,"reply_count":0,"crawler_target":{"resource_type":"social_media","stream_type":"account","specific_resource_type":"twitter","target_name":"332919636","extra_content":"Standupindo"},"entities":{"hashtags":[],"symbols":[],"user_mentions":[{"screen_name":"pandji","name":"Pandji Pragiwaksono","id":14305560,"id_str":"14305560","indices":[0,7]},{"screen_name":"Standupindo","name":"IG: standupindonesia","id":332919636,"id_str":"332919636","indices":[8,20]}],"urls":[]},"user_id":282551666,"display_text_range":[21,63],"contributors":null,"user":{"id":282551666,"id_str":"282551666","name":"kennedi","screen_name":"mathias_nedy","location":"","description":"\uD83D\uDC12     @steva_meirini","url":null,"entities":{"description":{"urls":[]}},"protected":false,"followers_count":418,"fast_followers_count":0,"normal_followers_count":418,"friends_count":332,"listed_count":1,"created_at":"Fri Apr 15 12:35:22 +0000 2011","favourites_count":1847,"utc_offset":null,"time_zone":null,"geo_enabled":true,"verified":false,"statuses_count":35369,"media_count":333,"lang":null,"contributors_enabled":false,"is_translator":false,"is_translation_enabled":false,"profile_background_color":"C0DEED","profile_background_image_url":"http://abs.twimg.com/images/themes/theme1/bg.png","profile_background_image_url_https":"https://abs.twimg.com/images/themes/theme1/bg.png","profile_background_tile":false,"profile_image_url":"http://pbs.twimg.com/profile_images/1464378880160980993/Y38t7rGs_normal.jpg","profile_image_url_https":"https://pbs.twimg.com/profile_images/1464378880160980993/Y38t7rGs_normal.jpg","profile_banner_url":"https://pbs.twimg.com/profile_banners/282551666/1627030686","profile_image_extensions_alt_text":null,"profile_image_extensions_media_availability":null,"profile_image_extensions_media_color":{"palette":[{"rgb":{"red":62,"green":61,"blue":59},"percentage":43.54},{"rgb":{"red":130,"green":121,"blue":116},"percentage":40.94},{"rgb":{"red":242,"green":247,"blue":245},"percentage":14.58},{"rgb":{"red":90,"green":113,"blue":133},"percentage":1.78},{"rgb":{"red":69,"green":98,"blue":119},"percentage":0.42}]},"profile_image_extensions":{"mediaStats":{"r":{"missing":null},"ttl":-1}},"profile_banner_extensions_alt_text":null,"profile_banner_extensions_media_availability":null,"profile_banner_extensions_media_color":{"palette":[{"rgb":{"red":254,"green":254,"blue":254},"percentage":84.1},{"rgb":{"red":127,"green":194,"blue":233},"percentage":5.25},{"rgb":{"red":64,"green":112,"blue":217},"percentage":2.82},{"rgb":{"red":36,"green":40,"blue":46},"percentage":2.07},{"rgb":{"red":89,"green":143,"blue":219},"percentage":2.03}]},"profile_banner_extensions":{"mediaStats":{"r":{"missing":null},"ttl":-1}},"profile_link_color":"0084B4","profile_sidebar_border_color":"000000","profile_sidebar_fill_color":"DDEEF6","profile_text_color":"333333","profile_use_background_image":true,"has_extended_profile":true,"default_profile":false,"default_profile_image":false,"pinned_tweet_ids":[],"pinned_tweet_ids_str":[],"has_custom_timelines":true,"can_dm":null,"following":null,"follow_request_sent":null,"notifications":null,"muting":null,"blocking":null,"blocked_by":null,"want_retweets":null,"advertiser_account_type":"promotable_user","advertiser_account_service_levels":["analytics"],"business_profile_state":"none","translator_type":"none","withheld_in_countries":[],"followed_by":null,"ext":{"highlightedLabel":{"r":{"ok":{}},"ttl":-1}},"require_some_consent":false}},{"in_reply_to_status_id_str":null,"in_reply_to_status_id":null,"supplemental_language":null,"created_at":"Tue May 15 04:09:51 +0000 2018","in_reply_to_user_id_str":null,"source":"<a href=\"http://twitter.com/download/iphone\" rel=\"nofollow\">Twitter for iPhone</a>","possibly_sensitive_editable":true,"quoted_status_id":996234428543193088,"retweet_count":1,"retweeted":false,"geo":null,"in_reply_to_screen_name":null,"is_quote_status":true,"user_id_str":"92960292","full_text":"Dukung @Arie_Kriting jadi Presiden @StandUpIndo. Awwe biar jadi Walikota Bekasi aja. \uD83D\uDE04 https://t.co/d3lzF9NWae","conversation_id":996241221352800257,"id_str":"996241221352800257","in_reply_to_user_id":null,"favorite_count":1,"id":996241221352800257,"place":{"id":"6c1ede2df1be1e0d","url":"https://api.twitter.com/1.1/geo/id/6c1ede2df1be1e0d.json","place_type":"city","name":"Matraman","full_name":"Matraman, Indonesia","country_code":"ID","country":"Indonesia","contained_within":[],"bounding_box":{"type":"Polygon","coordinates":[[[106.857762,-6.218042],[106.882085,-6.218042],[106.882085,-6.190618],[106.857762,-6.190618]]]},"attributes":{}},"quoted_status_permalink":{"url":"https://t.co/d3lzF9NWae","expanded":"https://twitter.com/awwe_/status/996234428543193088","display":"twitter.com/awwe_/status/9…"},"lang":"in","quote_count":0,"conversation_id_str":"996241221352800257","favorited":false,"possibly_sensitive":false,"coordinates":null,"truncated":false,"reply_count":0,"crawler_target":{"resource_type":"social_media","stream_type":"account","specific_resource_type":"twitter","target_name":"332919636","extra_content":"Standupindo"},"entities":{"hashtags":[],"symbols":[],"user_mentions":[{"screen_name":"Arie_Kriting","name":"JARINGAN PISGOR SAMBAL","id":102215394,"id_str":"102215394","indices":[7,20]},{"screen_name":"Standupindo","name":"IG: standupindonesia","id":332919636,"id_str":"332919636","indices":[35,47]}],"urls":[{"url":"https://t.co/d3lzF9NWae","expanded_url":"https://twitter.com/awwe_/status/996234428543193088","display_url":"twitter.com/awwe_/status/9…","indices":[87,110]}]},"user_id":92960292,"display_text_range":[0,86],"quoted_status_id_str":"996234428543193088","contributors":null,"user":{"id":92960292,"id_str":"92960292","name":"Andy Istiyono Han","screen_name":"andyistiyono","location":"Contact: +62 87777 366 933","description":"Talent Manager for Dicky Difie, Randhika Djamil, Yudha Brajamusti, Rachman Avri | IG: andyistiyono | #YNWA | #hejaBVB","url":null,"entities":{"description":{"urls":[]}},"protected":false,"followers_count":3634,"fast_followers_count":0,"normal_followers_count":3634,"friends_count":683,"listed_count":18,"created_at":"Fri Nov 27 12:33:00 +0000 2009","favourites_count":2094,"utc_offset":null,"time_zone":null,"geo_enabled":true,"verified":false,"statuses_count":68895,"media_count":5342,"lang":null,"contributors_enabled":false,"is_translator":false,"is_translation_enabled":false,"profile_background_color":"DBE9ED","profile_background_image_url":"http://abs.twimg.com/images/themes/theme7/bg.gif","profile_background_image_url_https":"https://abs.twimg.com/images/themes/theme7/bg.gif","profile_background_tile":true,"profile_image_url":"http://pbs.twimg.com/profile_images/1404230953371795457/SUCzQnRy_normal.jpg","profile_image_url_https":"https://pbs.twimg.com/profile_images/1404230953371795457/SUCzQnRy_normal.jpg","profile_banner_url":"https://pbs.twimg.com/profile_banners/92960292/1632656777","profile_image_extensions_alt_text":null,"profile_image_extensions_media_availability":null,"profile_image_extensions_media_color":{"palette":[{"rgb":{"red":226,"green":226,"blue":226},"percentage":78.96},{"rgb":{"red":31,"green":34,"blue":39},"percentage":19.4},{"rgb":{"red":132,"green":99,"blue":92},"percentage":0.69}]},"profile_image_extensions":{"mediaStats":{"r":{"missing":null},"ttl":-1}},"profile_banner_extensions_alt_text":null,"profile_banner_extensions_media_color":{"palette":[{"rgb":{"red":190,"green":199,"blue":194},"percentage":46.97},{"rgb":{"red":121,"green":105,"blue":92},"percentage":28.16},{"rgb":{"red":48,"green":53,"blue":57},"percentage":14.59},{"rgb":{"red":159,"green":128,"blue":69},"percentage":3.51},{"rgb":{"red":166,"green":158,"blue":63},"percentage":0.62}]},"profile_banner_extensions_media_availability":null,"profile_banner_extensions":{"mediaStats":{"r":{"missing":null},"ttl":-1}},"profile_link_color":"EB0E0E","profile_sidebar_border_color":"FFFFFF","profile_sidebar_fill_color":"F3F3F3","profile_text_color":"333333","profile_use_background_image":true,"has_extended_profile":true,"default_profile":false,"default_profile_image":false,"pinned_tweet_ids":[],"pinned_tweet_ids_str":[],"has_custom_timelines":false,"can_dm":null,"following":null,"follow_request_sent":null,"notifications":null,"muting":null,"blocking":null,"blocked_by":null,"want_retweets":null,"advertiser_account_type":"promotable_user","advertiser_account_service_levels":["analytics"],"business_profile_state":"none","translator_type":"none","withheld_in_countries":[],"followed_by":null,"ext":{"highlightedLabel":{"r":{"ok":{}},"ttl":-1}},"require_some_consent":false}},{"in_reply_to_status_id_str":"995969407867342849","in_reply_to_status_id":995969407867342849,"supplemental_language":null,"created_at":"Mon May 14 11:33:42 +0000 2018","in_reply_to_user_id_str":"14305560","source":"<a href=\"http://twitter.com/download/android\" rel=\"nofollow\">Twitter for Android</a>","retweet_count":0,"retweeted":false,"geo":null,"in_reply_to_screen_name":"pandji","is_quote_status":false,"user_id_str":"4420683378","full_text":"@pandji @StandUpIndo Loh kan ada @aniesbaswedan  Dan @sandiuno ,lu minta aja dari mereka duit,kan APBD DKI JAKARTA banyak @pandji ,masak TGUPP dikasih milyaran,lu yang paling loyal nggak kecipratan?.\nYang benar aja....?.\nduit 1milyard,untuk seorang @pandji ,masak nggak bisa disisihka dari APBD DKI?.","conversation_id":995969407867342849,"id_str":"995990534312230912","in_reply_to_user_id":14305560,"favorite_count":0,"id":995990534312230912,"place":null,"lang":"in","quote_count":0,"conversation_id_str":"995969407867342849","favorited":false,"coordinates":null,"truncated":false,"reply_count":0,"crawler_target":{"resource_type":"social_media","stream_type":"account","specific_resource_type":"twitter","target_name":"332919636","extra_content":"Standupindo"},"entities":{"hashtags":[],"symbols":[],"user_mentions":[{"screen_name":"pandji","name":"Pandji Pragiwaksono","id":14305560,"id_str":"14305560","indices":[0,7]},{"screen_name":"Standupindo","name":"IG: standupindonesia","id":332919636,"id_str":"332919636","indices":[8,20]},{"screen_name":"aniesbaswedan","name":"Anies Rasyid Baswedan | Sudah #VaksinDulu","id":110312278,"id_str":"110312278","indices":[33,47]},{"screen_name":"sandiuno","name":"Sandiaga Salahuddin Uno","id":132041617,"id_str":"132041617","indices":[53,62]},{"screen_name":"pandji","name":"Pandji Pragiwaksono","id":14305560,"id_str":"14305560","indices":[122,129]},{"screen_name":"pandji","name":"Pandji Pragiwaksono","id":14305560,"id_str":"14305560","indices":[249,256]}],"urls":[]},"user_id":4420683378,"display_text_range":[21,300],"contributors":null,"user":{"id":4420683378,"id_str":"4420683378","name":"CHANDRA SIMANJUNTAK","screen_name":"chandrajuni82","location":"Kota Pematang Siantar,SUMUT","description":"BUBARKAN SEMUA LEMBAGA-LEMBAGA ADDHOC PRODUK REFORMASI.\nSALAH SATUNYA KPK.","url":null,"entities":{"description":{"urls":[]}},"protected":false,"followers_count":268,"fast_followers_count":0,"normal_followers_count":268,"friends_count":472,"listed_count":0,"created_at":"Tue Dec 01 13:18:31 +0000 2015","favourites_count":1439,"utc_offset":null,"time_zone":null,"geo_enabled":false,"verified":false,"statuses_count":11861,"media_count":670,"lang":null,"contributors_enabled":false,"is_translator":false,"is_translation_enabled":false,"profile_background_color":"C0DEED","profile_background_image_url":"http://abs.twimg.com/images/themes/theme1/bg.png","profile_background_image_url_https":"https://abs.twimg.com/images/themes/theme1/bg.png","profile_background_tile":false,"profile_image_url":"http://pbs.twimg.com/profile_images/1461170631349735424/gsPvjYkm_normal.jpg","profile_image_url_https":"https://pbs.twimg.com/profile_images/1461170631349735424/gsPvjYkm_normal.jpg","profile_banner_url":"https://pbs.twimg.com/profile_banners/4420683378/1633536563","profile_image_extensions_media_color":{"palette":[{"rgb":{"red":207,"green":202,"blue":200},"percentage":58.64},{"rgb":{"red":52,"green":52,"blue":52},"percentage":22.98},{"rgb":{"red":125,"green":100,"blue":103},"percentage":1.46},{"rgb":{"red":108,"green":134,"blue":159},"percentage":1.15}]},"profile_image_extensions_alt_text":null,"profile_image_extensions_media_availability":null,"profile_image_extensions":{"mediaStats":{"r":{"missing":null},"ttl":-1}},"profile_banner_extensions_alt_text":null,"profile_banner_extensions_media_availability":null,"profile_banner_extensions_media_color":{"palette":[{"rgb":{"red":253,"green":254,"blue":254},"percentage":61.19},{"rgb":{"red":28,"green":75,"blue":75},"percentage":24.22},{"rgb":{"red":242,"green":5,"blue":5},"percentage":3.69},{"rgb":{"red":58,"green":42,"blue":44},"percentage":1.71},{"rgb":{"red":216,"green":56,"blue":55},"percentage":1.34}]},"profile_banner_extensions":{"mediaStats":{"r":{"missing":null},"ttl":-1}},"profile_link_color":"1DA1F2","profile_sidebar_border_color":"C0DEED","profile_sidebar_fill_color":"DDEEF6","profile_text_color":"333333","profile_use_background_image":true,"has_extended_profile":true,"default_profile":true,"default_profile_image":false,"pinned_tweet_ids":[],"pinned_tweet_ids_str":[],"has_custom_timelines":false,"can_dm":null,"following":null,"follow_request_sent":null,"notifications":null,"muting":null,"blocking":null,"blocked_by":null,"want_retweets":null,"advertiser_account_type":"promotable_user","advertiser_account_service_levels":[],"business_profile_state":"none","translator_type":"none","withheld_in_countries":[],"followed_by":null,"ext":{"highlightedLabel":{"r":{"ok":{}},"ttl":-1}},"require_some_consent":false}},{"in_reply_to_status_id_str":"996235541472411650","in_reply_to_status_id":996235541472411650,"supplemental_language":null,"created_at":"Tue May 15 06:01:52 +0000 2018","in_reply_to_user_id_str":"14305560","source":"<a href=\"https://mobile.twitter.com\" rel=\"nofollow\">Twitter Web App</a>","retweet_count":0,"retweeted":false,"geo":null,"in_reply_to_screen_name":"pandji","is_quote_status":false,"user_id_str":"921404174889132032","full_text":"@pandji @Arie_Kriting @StandUpIndo Bang @awwe memang sudah dua periode yah?\nKalo belum, kenapa engga DILAN JUTKAN ajah..","conversation_id":996235541472411650,"id_str":"996269414583492608","in_reply_to_user_id":14305560,"favorite_count":0,"id":996269414583492608,"place":null,"lang":"in","quote_count":0,"conversation_id_str":"996235541472411650","favorited":false,"coordinates":null,"truncated":false,"reply_count":0,"crawler_target":{"resource_type":"social_media","stream_type":"account","specific_resource_type":"twitter","target_name":"332919636","extra_content":"Standupindo"},"entities":{"hashtags":[],"symbols":[],"user_mentions":[{"screen_name":"pandji","name":"Pandji Pragiwaksono","id":14305560,"id_str":"14305560","indices":[0,7]},{"screen_name":"Arie_Kriting","name":"JARINGAN PISGOR SAMBAL","id":102215394,"id_str":"102215394","indices":[8,21]},{"screen_name":"Standupindo","name":"IG: standupindonesia","id":332919636,"id_str":"332919636","indices":[22,34]},{"screen_name":"awwE","name":"Eva","id":26023536,"id_str":"26023536","indices":[40,45]}],"urls":[]},"user_id":921404174889132032,"display_text_range":[35,120],"contributors":null,"user":{"id":921404174889132032,"id_str":"921404174889132032","name":"ujeUjenk19","screen_name":"ujeUjenk19","location":"","description":"","url":null,"entities":{"description":{"urls":[]}},"protected":false,"followers_count":3,"fast_followers_count":0,"normal_followers_count":3,"friends_count":63,"listed_count":0,"created_at":"Fri Oct 20 15:54:08 +0000 2017","favourites_count":137,"utc_offset":null,"time_zone":null,"geo_enabled":false,"verified":false,"statuses_count":266,"media_count":0,"lang":null,"contributors_enabled":false,"is_translator":false,"is_translation_enabled":false,"profile_background_color":"F5F8FA","profile_background_image_url":null,"profile_background_image_url_https":null,"profile_background_tile":false,"profile_image_url":"http://pbs.twimg.com/profile_images/921407245673414656/oV0bxUR0_normal.jpg","profile_image_url_https":"https://pbs.twimg.com/profile_images/921407245673414656/oV0bxUR0_normal.jpg","profile_banner_url":"https://pbs.twimg.com/profile_banners/921404174889132032/1520930437","profile_image_extensions_alt_text":null,"profile_image_extensions_media_color":{"palette":[{"rgb":{"red":253,"green":253,"blue":252},"percentage":64.32},{"rgb":{"red":124,"green":117,"blue":129},"percentage":29.58},{"rgb":{"red":238,"green":250,"blue":249},"percentage":2.53},{"rgb":{"red":183,"green":183,"blue":214},"percentage":1.67},{"rgb":{"red":210,"green":150,"blue":150},"percentage":1.5}]},"profile_image_extensions_media_availability":null,"profile_image_extensions":{"mediaStats":{"r":{"missing":null},"ttl":-1}},"profile_banner_extensions_media_color":{"palette":[{"rgb":{"red":0,"green":0,"blue":0},"percentage":87.94},{"rgb":{"red":254,"green":254,"blue":254},"percentage":9.21},{"rgb":{"red":101,"green":101,"blue":101},"percentage":3.56}]},"profile_banner_extensions_alt_text":null,"profile_banner_extensions_media_availability":null,"profile_banner_extensions":{"mediaStats":{"r":{"missing":null},"ttl":-1}},"profile_link_color":"1DA1F2","profile_sidebar_border_color":"C0DEED","profile_sidebar_fill_color":"DDEEF6","profile_text_color":"333333","profile_use_background_image":true,"has_extended_profile":false,"default_profile":true,"default_profile_image":false,"pinned_tweet_ids":[],"pinned_tweet_ids_str":[],"has_custom_timelines":false,"can_dm":null,"following":null,"follow_request_sent":null,"notifications":null,"muting":null,"blocking":null,"blocked_by":null,"want_retweets":null,"advertiser_account_type":"none","advertiser_account_service_levels":[],"business_profile_state":"none","translator_type":"none","withheld_in_countries":[],"followed_by":null,"ext":{"highlightedLabel":{"r":{"ok":{}},"ttl":-1}},"require_some_consent":false}},{"in_reply_to_status_id_str":"995969407867342849","in_reply_to_status_id":995969407867342849,"supplemental_language":null,"created_at":"Mon May 14 10:16:16 +0000 2018","in_reply_to_user_id_str":"14305560","source":"<a href=\"http://twitter.com/download/android\" rel=\"nofollow\">Twitter for Android</a>","retweet_count":0,"retweeted":false,"geo":null,"in_reply_to_screen_name":"pandji","is_quote_status":false,"user_id_str":"67300270","full_text":"@pandji @StandUpIndo bang, tanya...kalo beli tiketnya pas #TwivateConcert itu termasuk 2500 tiket wongsoyudan apa bukan?","conversation_id":995969407867342849,"id_str":"995971048326610944","in_reply_to_user_id":14305560,"favorite_count":0,"id":995971048326610944,"place":null,"lang":"in","quote_count":0,"conversation_id_str":"995969407867342849","favorited":false,"coordinates":null,"truncated":false,"reply_count":1,"crawler_target":{"resource_type":"social_media","stream_type":"account","specific_resource_type":"twitter","target_name":"332919636","extra_content":"Standupindo"},"entities":{"hashtags":[{"text":"TwivateConcert","indices":[58,73]}],"symbols":[],"user_mentions":[{"screen_name":"pandji","name":"Pandji Pragiwaksono","id":14305560,"id_str":"14305560","indices":[0,7]},{"screen_name":"Standupindo","name":"IG: standupindonesia","id":332919636,"id_str":"332919636","indices":[8,20]}],"urls":[]},"user_id":67300270,"display_text_range":[21,120],"contributors":null,"user":{"id":67300270,"id_str":"67300270","name":"Uchy Muharomi WSYDN","screen_name":"ucyucyucy","location":"Jakarta Selatan, DKI Jakarta","description":"just a (little) daughter of my parents, a youngest sister of my sisters & brothers, a cute aunt of my nieces & nephew and (i hope) a sweet wife of my husband ;)","url":"https://t.co/C5eIICPoE4","entities":{"url":{"urls":[{"url":"https://t.co/C5eIICPoE4","expanded_url":"https://www.instagram.com/puchydolls","display_url":"instagram.com/puchydolls","indices":[0,23]}]},"description":{"urls":[]}},"protected":false,"followers_count":280,"fast_followers_count":0,"normal_followers_count":280,"friends_count":255,"listed_count":0,"created_at":"Thu Aug 20 12:25:45 +0000 2009","favourites_count":971,"utc_offset":null,"time_zone":null,"geo_enabled":true,"verified":false,"statuses_count":18010,"media_count":904,"lang":null,"contributors_enabled":false,"is_translator":false,"is_translation_enabled":false,"profile_background_color":"94D487","profile_background_image_url":"http://abs.twimg.com/images/themes/theme5/bg.gif","profile_background_image_url_https":"https://abs.twimg.com/images/themes/theme5/bg.gif","profile_background_tile":true,"profile_image_url":"http://pbs.twimg.com/profile_images/1008749542831878144/jKQM56PB_normal.jpg","profile_image_url_https":"https://pbs.twimg.com/profile_images/1008749542831878144/jKQM56PB_normal.jpg","profile_banner_url":"https://pbs.twimg.com/profile_banners/67300270/1529339613","profile_image_extensions_media_color":{"palette":[{"rgb":{"red":200,"green":201,"blue":219},"percentage":44.57},{"rgb":{"red":161,"green":108,"blue":113},"percentage":20.7},{"rgb":{"red":178,"green":98,"blue":170},"percentage":8.02},{"rgb":{"red":57,"green":44,"blue":52},"percentage":6.93},{"rgb":{"red":175,"green":189,"blue":221},"percentage":5.64}]},"profile_image_extensions_alt_text":null,"profile_image_extensions_media_availability":null,"profile_image_extensions":{"mediaStats":{"r":{"missing":null},"ttl":-1}},"profile_banner_extensions_media_color":{"palette":[{"rgb":{"red":80,"green":45,"blue":14},"percentage":89.12},{"rgb":{"red":29,"green":15,"blue":4},"percentage":5.45},{"rgb":{"red":88,"green":39,"blue":14},"percentage":3.62},{"rgb":{"red":78,"green":77,"blue":63},"percentage":0.45},{"rgb":{"red":109,"green":61,"blue":20},"percentage":0.31}]},"profile_banner_extensions_alt_text":null,"profile_banner_extensions_media_availability":null,"profile_banner_extensions":{"mediaStats":{"r":{"missing":null},"ttl":-1}},"profile_link_color":"369854","profile_sidebar_border_color":"FFFFFF","profile_sidebar_fill_color":"FDFFD1","profile_text_color":"0C4A61","profile_use_background_image":true,"has_extended_profile":false,"default_profile":false,"default_profile_image":false,"pinned_tweet_ids":[],"pinned_tweet_ids_str":[],"has_custom_timelines":true,"can_dm":null,"following":null,"follow_request_sent":null,"notifications":null,"muting":null,"blocking":null,"blocked_by":null,"want_retweets":null,"advertiser_account_type":"none","advertiser_account_service_levels":[],"business_profile_state":"none","translator_type":"none","withheld_in_countries":[],"followed_by":null,"ext":{"highlightedLabel":{"r":{"ok":{}},"ttl":-1}},"require_some_consent":false}},{"in_reply_to_status_id_str":null,"in_reply_to_status_id":null,"supplemental_language":null,"created_at":"Tue May 15 03:47:16 +0000 2018","in_reply_to_user_id_str":null,"source":"<a href=\"http://twitter.com/download/iphone\" rel=\"nofollow\">Twitter for iPhone</a>","possibly_sensitive_editable":true,"quoted_status_id":996234428543193088,"retweet_count":5,"retweeted":false,"geo":null,"in_reply_to_screen_name":null,"is_quote_status":true,"user_id_str":"14305560","full_text":"DUKUNG @Arie_Kriting SEBAGAI PRESIDEN @STANDUPINDO https://t.co/iLn1MnyLEo","conversation_id":996235541472411650,"id_str":"996235541472411650","in_reply_to_user_id":null,"favorite_count":8,"id":996235541472411650,"place":null,"quoted_status_permalink":{"url":"https://t.co/iLn1MnyLEo","expanded":"https://twitter.com/awwe_/status/996234428543193088","display":"twitter.com/awwe_/status/9…"},"lang":"in","quote_count":0,"conversation_id_str":"996235541472411650","favorited":false,"possibly_sensitive":false,"coordinates":null,"truncated":false,"reply_count":4,"crawler_target":{"resource_type":"social_media","stream_type":"account","specific_resource_type":"twitter","target_name":"332919636","extra_content":"Standupindo"},"entities":{"hashtags":[],"symbols":[],"user_mentions":[{"screen_name":"Arie_Kriting","name":"JARINGAN PISGOR SAMBAL","id":102215394,"id_str":"102215394","indices":[7,20]},{"screen_name":"Standupindo","name":"IG: standupindonesia","id":332919636,"id_str":"332919636","indices":[38,50]}],"urls":[{"url":"https://t.co/iLn1MnyLEo","expanded_url":"https://twitter.com/awwe_/status/996234428543193088","display_url":"twitter.com/awwe_/status/9…","indices":[51,74]}]},"user_id":14305560,"display_text_range":[0,50],"quoted_status_id_str":"996234428543193088","contributors":null,"user":{"id":14305560,"id_str":"14305560","name":"Pandji Pragiwaksono","screen_name":"pandji","location":"Indonesia","description":"Stand-Up Comedian with 8 Special who is now running COMIKA, a company devoted to create the world a funnier place.","url":"https://t.co/SEa8vNPYbA","entities":{"url":{"urls":[{"url":"https://t.co/SEa8vNPYbA","expanded_url":"https://linktr.ee/pandji.pragiwaksono","display_url":"linktr.ee/pandji.pragiwa…","indices":[0,23]}]},"description":{"urls":[]}},"protected":false,"followers_count":1572888,"fast_followers_count":0,"normal_followers_count":1572888,"friends_count":346,"listed_count":1566,"created_at":"Fri Apr 04 19:35:56 +0000 2008","favourites_count":2230,"utc_offset":null,"time_zone":null,"geo_enabled":true,"verified":true,"statuses_count":270177,"media_count":24117,"lang":null,"contributors_enabled":false,"is_translator":false,"is_translation_enabled":false,"profile_background_color":"000000","profile_background_image_url":"http://abs.twimg.com/images/themes/theme1/bg.png","profile_background_image_url_https":"https://abs.twimg.com/images/themes/theme1/bg.png","profile_background_tile":false,"profile_image_url":"http://pbs.twimg.com/profile_images/1341056153468354574/kcfQnHeI_normal.jpg","profile_image_url_https":"https://pbs.twimg.com/profile_images/1341056153468354574/kcfQnHeI_normal.jpg","profile_banner_url":"https://pbs.twimg.com/profile_banners/14305560/1608097720","profile_image_extensions_alt_text":null,"profile_image_extensions_media_availability":null,"profile_image_extensions_media_color":{"palette":[{"rgb":{"red":177,"green":184,"blue":190},"percentage":40.08},{"rgb":{"red":39,"green":47,"blue":35},"percentage":32.09},{"rgb":{"red":115,"green":114,"blue":97},"percentage":10},{"rgb":{"red":14,"green":42,"blue":56},"percentage":6.72},{"rgb":{"red":68,"green":75,"blue":34},"percentage":5.21}]},"profile_image_extensions":{"mediaStats":{"r":{"missing":null},"ttl":-1}},"profile_banner_extensions_alt_text":null,"profile_banner_extensions_media_availability":null,"profile_banner_extensions_media_color":{"palette":[{"rgb":{"red":162,"green":161,"blue":162},"percentage":76.76},{"rgb":{"red":38,"green":45,"blue":51},"percentage":19.59},{"rgb":{"red":213,"green":190,"blue":175},"percentage":0.18},{"rgb":{"red":44,"green":40,"blue":26},"percentage":0.16}]},"profile_banner_extensions":{"mediaStats":{"r":{"missing":null},"ttl":-1}},"profile_link_color":"3CB904","profile_sidebar_border_color":"164700","profile_sidebar_fill_color":"255211","profile_text_color":"979595","profile_use_background_image":true,"has_extended_profile":true,"default_profile":false,"default_profile_image":false,"pinned_tweet_ids":[],"pinned_tweet_ids_str":[],"has_custom_timelines":true,"can_dm":null,"following":null,"follow_request_sent":null,"notifications":null,"muting":null,"blocking":null,"blocked_by":null,"want_retweets":null,"advertiser_account_type":"promotable_user","advertiser_account_service_levels":["analytics"],"business_profile_state":"none","translator_type":"regular","withheld_in_countries":[],"followed_by":null,"ext":{"highlightedLabel":{"r":{"ok":{}},"ttl":-1}},"require_some_consent":false}},{"in_reply_to_status_id_str":"996235541472411650","in_reply_to_status_id":996235541472411650,"supplemental_language":null,"created_at":"Tue May 15 04:00:52 +0000 2018","in_reply_to_user_id_str":"14305560","source":"<a href=\"http://twitter.com/download/android\" rel=\"nofollow\">Twitter for Android</a>","retweet_count":0,"retweeted":false,"geo":null,"in_reply_to_screen_name":"pandji","is_quote_status":false,"user_id_str":"135309415","full_text":"@pandji @Arie_Kriting @StandUpIndo Gua orang timur tapi kaga mau klo @Arie_Kriting yg presiden @standupindo","conversation_id":996235541472411650,"id_str":"996238963290484736","in_reply_to_user_id":14305560,"favorite_count":0,"id":996238963290484736,"place":null,"lang":"in","quote_count":0,"conversation_id_str":"996235541472411650","favorited":false,"coordinates":null,"truncated":false,"reply_count":0,"crawler_target":{"resource_type":"social_media","stream_type":"account","specific_resource_type":"twitter","target_name":"332919636","extra_content":"Standupindo"},"entities":{"hashtags":[],"symbols":[],"user_mentions":[{"screen_name":"pandji","name":"Pandji Pragiwaksono","id":14305560,"id_str":"14305560","indices":[0,7]},{"screen_name":"Arie_Kriting","name":"JARINGAN PISGOR SAMBAL","id":102215394,"id_str":"102215394","indices":[8,21]},{"screen_name":"Standupindo","name":"IG: standupindonesia","id":332919636,"id_str":"332919636","indices":[22,34]},{"screen_name":"Arie_Kriting","name":"JARINGAN PISGOR SAMBAL","id":102215394,"id_str":"102215394","indices":[69,82]},{"screen_name":"Standupindo","name":"IG: standupindonesia","id":332919636,"id_str":"332919636","indices":[95,107]}],"urls":[]},"user_id":135309415,"display_text_range":[35,107],"contributors":null,"user":{"id":135309415,"id_str":"135309415","name":"alfian ismail","screen_name":"Alfian_Ismaill","location":"Jakarta Pusat, DKI Jakarta","description":"poto poto apa aja","url":null,"entities":{"description":{"urls":[]}},"protected":false,"followers_count":518,"fast_followers_count":0,"normal_followers_count":518,"friends_count":704,"listed_count":2,"created_at":"Tue Apr 20 23:24:08 +0000 2010","favourites_count":11376,"utc_offset":null,"time_zone":null,"geo_enabled":true,"verified":false,"statuses_count":12082,"media_count":568,"lang":null,"contributors_enabled":false,"is_translator":false,"is_translation_enabled":false,"profile_background_color":"131516","profile_background_image_url":"http://abs.twimg.com/images/themes/theme14/bg.gif","profile_background_image_url_https":"https://abs.twimg.com/images/themes/theme14/bg.gif","profile_background_tile":true,"profile_image_url":"http://pbs.twimg.com/profile_images/1420783303947276292/xuco_Pbj_normal.jpg","profile_image_url_https":"https://pbs.twimg.com/profile_images/1420783303947276292/xuco_Pbj_normal.jpg","profile_banner_url":"https://pbs.twimg.com/profile_banners/135309415/1407809491","profile_image_extensions_alt_text":null,"profile_image_extensions_media_availability":null,"profile_image_extensions_media_color":{"palette":[{"rgb":{"red":70,"green":71,"blue":85},"percentage":60.47},{"rgb":{"red":116,"green":118,"blue":139},"percentage":36.22},{"rgb":{"red":217,"green":217,"blue":227},"percentage":3.01},{"rgb":{"red":135,"green":106,"blue":107},"percentage":0.2}]},"profile_image_extensions":{"mediaStats":{"r":{"missing":null},"ttl":-1}},"profile_banner_extensions_alt_text":null,"profile_banner_extensions_media_availability":null,"profile_banner_extensions_media_color":{"palette":[{"rgb":{"red":72,"green":72,"blue":70},"percentage":42.86},{"rgb":{"red":209,"green":209,"blue":209},"percentage":38.75},{"rgb":{"red":130,"green":130,"blue":121},"percentage":0.87}]},"profile_banner_extensions":{"mediaStats":{"r":{"missing":null},"ttl":-1}},"profile_link_color":"009999","profile_sidebar_border_color":"EEEEEE","profile_sidebar_fill_color":"EFEFEF","profile_text_color":"333333","profile_use_background_image":true,"has_extended_profile":false,"default_profile":false,"default_profile_image":false,"pinned_tweet_ids":[810147766617841665],"pinned_tweet_ids_str":["810147766617841665"],"has_custom_timelines":true,"can_dm":null,"following":null,"follow_request_sent":null,"notifications":null,"muting":null,"blocking":null,"blocked_by":null,"want_retweets":null,"advertiser_account_type":"promotable_user","advertiser_account_service_levels":[],"business_profile_state":"none","translator_type":"none","withheld_in_countries":[],"followed_by":null,"ext":{"highlightedLabel":{"r":{"ok":{}},"ttl":-1}},"require_some_consent":false}},{"in_reply_to_status_id_str":null,"in_reply_to_status_id":null,"supplemental_language":null,"created_at":"Mon May 14 10:09:45 +0000 2018","in_reply_to_user_id_str":null,"source":"<a href=\"http://instagram.com\" rel=\"nofollow\">Instagram</a>","possibly_sensitive_editable":true,"retweet_count":2,"retweeted":false,"geo":null,"in_reply_to_screen_name":null,"is_quote_status":false,"user_id_str":"14305560","full_text":"Wahai para penonton @StandUpIndo , gue punya pesan spesial untuk elo :) https://t.co/L19oFoSlMi","conversation_id":995969407867342849,"id_str":"995969407867342849","in_reply_to_user_id":null,"favorite_count":8,"id":995969407867342849,"place":null,"lang":"in","quote_count":1,"conversation_id_str":"995969407867342849","favorited":false,"possibly_sensitive":false,"coordinates":null,"truncated":false,"reply_count":3,"crawler_target":{"resource_type":"social_media","stream_type":"account","specific_resource_type":"twitter","target_name":"332919636","extra_content":"Standupindo"},"entities":{"hashtags":[],"symbols":[],"user_mentions":[{"screen_name":"Standupindo","name":"IG: standupindonesia","id":332919636,"id_str":"332919636","indices":[20,32]}],"urls":[{"url":"https://t.co/L19oFoSlMi","expanded_url":"https://www.instagram.com/p/BiwQRmSFrsL/?utm_source=ig_twitter_share","display_url":"instagram.com/p/BiwQRmSFrsL/…","indices":[72,95]}]},"user_id":14305560,"display_text_range":[0,95],"contributors":null,"user":{"id":14305560,"id_str":"14305560","name":"Pandji Pragiwaksono","screen_name":"pandji","location":"Indonesia","description":"Stand-Up Comedian with 8 Special who is now running COMIKA, a company devoted to create the world a funnier place.","url":"https://t.co/SEa8vNPYbA","entities":{"url":{"urls":[{"url":"https://t.co/SEa8vNPYbA","expanded_url":"https://linktr.ee/pandji.pragiwaksono","display_url":"linktr.ee/pandji.pragiwa…","indices":[0,23]}]},"description":{"urls":[]}},"protected":false,"followers_count":1572888,"fast_followers_count":0,"normal_followers_count":1572888,"friends_count":346,"listed_count":1566,"created_at":"Fri Apr 04 19:35:56 +0000 2008","favourites_count":2230,"utc_offset":null,"time_zone":null,"geo_enabled":true,"verified":true,"statuses_count":270177,"media_count":24117,"lang":null,"contributors_enabled":false,"is_translator":false,"is_translation_enabled":false,"profile_background_color":"000000","profile_background_image_url":"http://abs.twimg.com/images/themes/theme1/bg.png","profile_background_image_url_https":"https://abs.twimg.com/images/themes/theme1/bg.png","profile_background_tile":false,"profile_image_url":"http://pbs.twimg.com/profile_images/1341056153468354574/kcfQnHeI_normal.jpg","profile_image_url_https":"https://pbs.twimg.com/profile_images/1341056153468354574/kcfQnHeI_normal.jpg","profile_banner_url":"https://pbs.twimg.com/profile_banners/14305560/1608097720","profile_image_extensions_alt_text":null,"profile_image_extensions_media_availability":null,"profile_image_extensions_media_color":{"palette":[{"rgb":{"red":177,"green":184,"blue":190},"percentage":40.08},{"rgb":{"red":39,"green":47,"blue":35},"percentage":32.09},{"rgb":{"red":115,"green":114,"blue":97},"percentage":10},{"rgb":{"red":14,"green":42,"blue":56},"percentage":6.72},{"rgb":{"red":68,"green":75,"blue":34},"percentage":5.21}]},"profile_image_extensions":{"mediaStats":{"r":{"missing":null},"ttl":-1}},"profile_banner_extensions_alt_text":null,"profile_banner_extensions_media_availability":null,"profile_banner_extensions_media_color":{"palette":[{"rgb":{"red":162,"green":161,"blue":162},"percentage":76.76},{"rgb":{"red":38,"green":45,"blue":51},"percentage":19.59},{"rgb":{"red":213,"green":190,"blue":175},"percentage":0.18},{"rgb":{"red":44,"green":40,"blue":26},"percentage":0.16}]},"profile_banner_extensions":{"mediaStats":{"r":{"missing":null},"ttl":-1}},"profile_link_color":"3CB904","profile_sidebar_border_color":"164700","profile_sidebar_fill_color":"255211","profile_text_color":"979595","profile_use_background_image":true,"has_extended_profile":true,"default_profile":false,"default_profile_image":false,"pinned_tweet_ids":[],"pinned_tweet_ids_str":[],"has_custom_timelines":true,"can_dm":null,"following":null,"follow_request_sent":null,"notifications":null,"muting":null,"blocking":null,"blocked_by":null,"want_retweets":null,"advertiser_account_type":"promotable_user","advertiser_account_service_levels":["analytics"],"business_profile_state":"none","translator_type":"regular","withheld_in_countries":[],"followed_by":null,"ext":{"highlightedLabel":{"r":{"ok":{}},"ttl":-1}},"require_some_consent":false}},{"in_reply_to_status_id_str":"996235541472411650","in_reply_to_status_id":996235541472411650,"supplemental_language":null,"created_at":"Tue May 15 10:22:53 +0000 2018","in_reply_to_user_id_str":"14305560","source":"<a href=\"http://twitter.com/download/android\" rel=\"nofollow\">Twitter for Android</a>","retweet_count":0,"retweeted":false,"geo":null,"in_reply_to_screen_name":"pandji","is_quote_status":false,"user_id_str":"534430074","full_text":"@pandji @Arie_Kriting @StandUpIndo Saya dukung Bakriyadi, biar semua komika punya motivasi hidup.","conversation_id":996235541472411650,"id_str":"996335098671783938","in_reply_to_user_id":14305560,"favorite_count":0,"id":996335098671783938,"place":null,"lang":"in","quote_count":0,"conversation_id_str":"996235541472411650","favorited":false,"coordinates":null,"truncated":false,"reply_count":0,"crawler_target":{"resource_type":"social_media","stream_type":"account","specific_resource_type":"twitter","target_name":"332919636","extra_content":"Standupindo"},"entities":{"hashtags":[],"symbols":[],"user_mentions":[{"screen_name":"pandji","name":"Pandji Pragiwaksono","id":14305560,"id_str":"14305560","indices":[0,7]},{"screen_name":"Arie_Kriting","name":"JARINGAN PISGOR SAMBAL","id":102215394,"id_str":"102215394","indices":[8,21]},{"screen_name":"Standupindo","name":"IG: standupindonesia","id":332919636,"id_str":"332919636","indices":[22,34]}],"urls":[]},"user_id":534430074,"display_text_range":[35,97],"contributors":null,"user":{"id":534430074,"id_str":"534430074","name":"UCHENK","screen_name":"AndiUchenk","location":"manado, indonesia","description":"","url":"https://t.co/40m9knt4cF","entities":{"url":{"urls":[{"url":"https://t.co/40m9knt4cF","expanded_url":"http://ucenkandi.blogspot.com","display_url":"ucenkandi.blogspot.com","indices":[0,23]}]},"description":{"urls":[]}},"protected":false,"followers_count":189,"fast_followers_count":0,"normal_followers_count":189,"friends_count":285,"listed_count":0,"created_at":"Fri Mar 23 14:17:17 +0000 2012","favourites_count":172,"utc_offset":null,"time_zone":null,"geo_enabled":true,"verified":false,"statuses_count":2039,"media_count":36,"lang":null,"contributors_enabled":false,"is_translator":false,"is_translation_enabled":false,"profile_background_color":"131516","profile_background_image_url":"http://abs.twimg.com/images/themes/theme14/bg.gif","profile_background_image_url_https":"https://abs.twimg.com/images/themes/theme14/bg.gif","profile_background_tile":true,"profile_image_url":"http://pbs.twimg.com/profile_images/1392886818488520706/Nk5KQBB-_normal.jpg","profile_image_url_https":"https://pbs.twimg.com/profile_images/1392886818488520706/Nk5KQBB-_normal.jpg","profile_banner_url":"https://pbs.twimg.com/profile_banners/534430074/1579298529","profile_image_extensions_media_color":{"palette":[{"rgb":{"red":37,"green":41,"blue":44},"percentage":43.3},{"rgb":{"red":168,"green":163,"blue":161},"percentage":32.12},{"rgb":{"red":137,"green":74,"blue":51},"percentage":14.07},{"rgb":{"red":76,"green":59,"blue":53},"percentage":5.37},{"rgb":{"red":191,"green":138,"blue":120},"percentage":2.42}]},"profile_image_extensions_alt_text":null,"profile_image_extensions_media_availability":null,"profile_image_extensions":{"mediaStats":{"r":{"missing":null},"ttl":-1}},"profile_banner_extensions_alt_text":null,"profile_banner_extensions_media_availability":null,"profile_banner_extensions_media_color":{"palette":[{"rgb":{"red":39,"green":47,"blue":64},"percentage":83.67},{"rgb":{"red":184,"green":159,"blue":156},"percentage":13.26},{"rgb":{"red":142,"green":105,"blue":103},"percentage":1.96},{"rgb":{"red":139,"green":155,"blue":166},"percentage":0.58},{"rgb":{"red":116,"green":90,"blue":91},"percentage":0.49}]},"profile_banner_extensions":{"mediaStats":{"r":{"missing":null},"ttl":-1}},"profile_link_color":"3B94D9","profile_sidebar_border_color":"EEEEEE","profile_sidebar_fill_color":"EFEFEF","profile_text_color":"333333","profile_use_background_image":true,"has_extended_profile":false,"default_profile":false,"default_profile_image":false,"pinned_tweet_ids":[],"pinned_tweet_ids_str":[],"has_custom_timelines":false,"can_dm":null,"following":null,"follow_request_sent":null,"notifications":null,"muting":null,"blocking":null,"blocked_by":null,"want_retweets":null,"advertiser_account_type":"none","advertiser_account_service_levels":[],"business_profile_state":"none","translator_type":"none","withheld_in_countries":[],"followed_by":null,"ext":{"highlightedLabel":{"r":{"ok":{}},"ttl":-1}},"require_some_consent":false}},{"in_reply_to_status_id_str":"996421009338085376","in_reply_to_status_id":996421009338085376,"supplemental_language":null,"created_at":"Tue May 15 21:40:29 +0000 2018","in_reply_to_user_id_str":"2647216680","source":"<a href=\"http://twitter.com/download/android\" rel=\"nofollow\">Twitter for Android</a>","retweet_count":2,"retweeted":false,"geo":null,"in_reply_to_screen_name":"Ra_Ria_Rana","is_quote_status":false,"user_id_str":"465344647","full_text":"@Ra_Ria_Rana @dapitdong @kangsemproel @Aslicila @Fariz_semewew Inilah bukti nyata bong200..  kecepatan berfikir kalah cepat sama kecepatan ngetuit.. makanya mikir dlu sblum melakukan apapun. Otak dipake.. minta voucher isi ulang otak sm ernest noh @uusbiasaaja malu2in @StandUpIndo aj","conversation_id":996421009338085376,"id_str":"996505623406698496","in_reply_to_user_id":2647216680,"favorite_count":5,"id":996505623406698496,"place":null,"lang":"in","quote_count":0,"conversation_id_str":"996421009338085376","favorited":false,"coordinates":null,"truncated":false,"reply_count":0,"crawler_target":{"resource_type":"social_media","stream_type":"account","specific_resource_type":"twitter","target_name":"332919636","extra_content":"Standupindo"},"entities":{"hashtags":[],"symbols":[],"user_mentions":[{"screen_name":"Ra_Ria_Rana","name":"Citra Heriadi Kirana_RANA","id":2647216680,"id_str":"2647216680","indices":[0,12]},{"screen_name":"dapitdong","name":"David Usman","id":63941034,"id_str":"63941034","indices":[13,23]},{"screen_name":"KangSemproel","name":"Hilik Ku Aink Wae Lah✌","id":963751550,"id_str":"963751550","indices":[24,37]},{"screen_name":"Aslicila","name":"R Te Jamil..","id":2215261891,"id_str":"2215261891","indices":[38,47]},{"screen_name":"uusbiasaaja","name":"tiga huruf dari banyak huruf","id":78879048,"id_str":"78879048","indices":[248,260]},{"screen_name":"Standupindo","name":"IG: standupindonesia","id":332919636,"id_str":"332919636","indices":[269,281]}],"urls":[]},"user_id":465344647,"display_text_range":[63,284],"contributors":null,"user":{"id":465344647,"id_str":"465344647","name":"xkdnsbsbejkal hindariUUITE","screen_name":"qq_arsenal","location":"Bogoro, Nigeria","description":"pasti ada jalannyaa...","url":null,"entities":{"description":{"urls":[]}},"protected":false,"followers_count":117,"fast_followers_count":0,"normal_followers_count":117,"friends_count":286,"listed_count":0,"created_at":"Mon Jan 16 07:32:41 +0000 2012","favourites_count":855,"utc_offset":null,"time_zone":null,"geo_enabled":true,"verified":false,"statuses_count":2058,"media_count":58,"lang":null,"contributors_enabled":false,"is_translator":false,"is_translation_enabled":false,"profile_background_color":"EDECE9","profile_background_image_url":"http://abs.twimg.com/images/themes/theme3/bg.gif","profile_background_image_url_https":"https://abs.twimg.com/images/themes/theme3/bg.gif","profile_background_tile":true,"profile_image_url":"http://pbs.twimg.com/profile_images/1318114140817219585/86C5-jGo_normal.jpg","profile_image_url_https":"https://pbs.twimg.com/profile_images/1318114140817219585/86C5-jGo_normal.jpg","profile_banner_url":"https://pbs.twimg.com/profile_banners/465344647/1603097825","profile_image_extensions_alt_text":null,"profile_image_extensions_media_availability":null,"profile_image_extensions_media_color":{"palette":[{"rgb":{"red":21,"green":16,"blue":11},"percentage":73.36},{"rgb":{"red":66,"green":18,"blue":17},"percentage":9.12},{"rgb":{"red":140,"green":118,"blue":106},"percentage":6.93},{"rgb":{"red":134,"green":30,"blue":33},"percentage":4.89},{"rgb":{"red":86,"green":58,"blue":36},"percentage":0.98}]},"profile_image_extensions":{"mediaStats":{"r":{"missing":null},"ttl":-1}},"profile_banner_extensions_alt_text":null,"profile_banner_extensions_media_availability":null,"profile_banner_extensions_media_color":{"palette":[{"rgb":{"red":230,"green":232,"blue":215},"percentage":88.32},{"rgb":{"red":105,"green":99,"blue":85},"percentage":9.87},{"rgb":{"red":157,"green":114,"blue":108},"percentage":1.74}]},"profile_banner_extensions":{"mediaStats":{"r":{"missing":null},"ttl":-1}},"profile_link_color":"C737C2","profile_sidebar_border_color":"D3D2CF","profile_sidebar_fill_color":"E3E2DE","profile_text_color":"634047","profile_use_background_image":true,"has_extended_profile":true,"default_profile":false,"default_profile_image":false,"pinned_tweet_ids":[],"pinned_tweet_ids_str":[],"has_custom_timelines":true,"can_dm":null,"following":null,"follow_request_sent":null,"notifications":null,"muting":null,"blocking":null,"blocked_by":null,"want_retweets":null,"advertiser_account_type":"promotable_user","advertiser_account_service_levels":["analytics"],"business_profile_state":"none","translator_type":"none","withheld_in_countries":[],"followed_by":null,"ext":{"highlightedLabel":{"r":{"ok":{}},"ttl":-1}},"require_some_consent":false}},{"in_reply_to_status_id_str":"996235541472411650","in_reply_to_status_id":996235541472411650,"supplemental_language":null,"created_at":"Tue May 15 03:50:46 +0000 2018","in_reply_to_user_id_str":"14305560","source":"<a href=\"http://twitter.com/download/android\" rel=\"nofollow\">Twitter for Android</a>","retweet_count":0,"retweeted":false,"geo":null,"in_reply_to_screen_name":"pandji","is_quote_status":false,"user_id_str":"546461615","full_text":"@pandji @Arie_Kriting @StandUpIndo Bikin polling dong, siapa aja nih calon nya kalo bener hihi","conversation_id":996235541472411650,"id_str":"996236419797434368","in_reply_to_user_id":14305560,"favorite_count":0,"id":996236419797434368,"place":null,"lang":"in","quote_count":0,"conversation_id_str":"996235541472411650","favorited":false,"coordinates":null,"truncated":false,"reply_count":0,"crawler_target":{"resource_type":"social_media","stream_type":"account","specific_resource_type":"twitter","target_name":"332919636","extra_content":"Standupindo"},"entities":{"hashtags":[],"symbols":[],"user_mentions":[{"screen_name":"pandji","name":"Pandji Pragiwaksono","id":14305560,"id_str":"14305560","indices":[0,7]},{"screen_name":"Arie_Kriting","name":"JARINGAN PISGOR SAMBAL","id":102215394,"id_str":"102215394","indices":[8,21]},{"screen_name":"Standupindo","name":"IG: standupindonesia","id":332919636,"id_str":"332919636","indices":[22,34]}],"urls":[]},"user_id":546461615,"display_text_range":[35,94],"contributors":null,"user":{"id":546461615,"id_str":"546461615","name":"Alexander Supertramp","screen_name":"AbiAyaIeuNyag","location":"Ladang","description":"Pohon Tidak Tumbuh Tergesa-gesa","url":"https://t.co/iNtSzvqLiv","entities":{"url":{"urls":[{"url":"https://t.co/iNtSzvqLiv","expanded_url":"https://open.spotify.com/playlist/3JdVuRxYZDLWnmmEUcyMRd?si=hBqUMSRwQ7WlyBZyqDVPfg&utm_source=copy-l","display_url":"open.spotify.com/playlist/3JdVu…","indices":[0,23]}]},"description":{"urls":[]}},"protected":false,"followers_count":196,"fast_followers_count":0,"normal_followers_count":196,"friends_count":540,"listed_count":0,"created_at":"Fri Apr 06 02:53:06 +0000 2012","favourites_count":6166,"utc_offset":null,"time_zone":null,"geo_enabled":true,"verified":false,"statuses_count":6864,"media_count":393,"lang":null,"contributors_enabled":false,"is_translator":false,"is_translation_enabled":false,"profile_background_color":"A8DE6A","profile_background_image_url":"http://abs.twimg.com/images/themes/theme14/bg.gif","profile_background_image_url_https":"https://abs.twimg.com/images/themes/theme14/bg.gif","profile_background_tile":true,"profile_image_url":"http://pbs.twimg.com/profile_images/1416065326144364545/NnoTV7Gh_normal.jpg","profile_image_url_https":"https://pbs.twimg.com/profile_images/1416065326144364545/NnoTV7Gh_normal.jpg","profile_banner_url":"https://pbs.twimg.com/profile_banners/546461615/1638797762","profile_image_extensions_alt_text":null,"profile_image_extensions_media_availability":null,"profile_image_extensions_media_color":{"palette":[{"rgb":{"red":9,"green":9,"blue":9},"percentage":71.36},{"rgb":{"red":187,"green":188,"blue":180},"percentage":6.74},{"rgb":{"red":101,"green":62,"blue":43},"percentage":3.75},{"rgb":{"red":32,"green":58,"blue":90},"percentage":3.57},{"rgb":{"red":89,"green":86,"blue":61},"percentage":1.6}]},"profile_image_extensions":{"mediaStats":{"r":{"missing":null},"ttl":-1}},"profile_banner_extensions_media_color":{"palette":[{"rgb":{"red":41,"green":44,"blue":41},"percentage":48.89},{"rgb":{"red":235,"green":236,"blue":233},"percentage":34.32},{"rgb":{"red":87,"green":70,"blue":59},"percentage":1.53},{"rgb":{"red":187,"green":160,"blue":143},"percentage":1.47},{"rgb":{"red":206,"green":242,"blue":247},"percentage":0.62}]},"profile_banner_extensions_alt_text":null,"profile_banner_extensions_media_availability":null,"profile_banner_extensions":{"mediaStats":{"r":{"missing":null},"ttl":-1}},"profile_link_color":"6B5154","profile_sidebar_border_color":"FFFFFF","profile_sidebar_fill_color":"EFEFEF","profile_text_color":"333333","profile_use_background_image":true,"has_extended_profile":true,"default_profile":false,"default_profile_image":false,"pinned_tweet_ids":[1042121734067871744],"pinned_tweet_ids_str":["1042121734067871744"],"has_custom_timelines":true,"can_dm":null,"following":null,"follow_request_sent":null,"notifications":null,"muting":null,"blocking":null,"blocked_by":null,"want_retweets":null,"advertiser_account_type":"promotable_user","advertiser_account_service_levels":[],"business_profile_state":"none","translator_type":"none","withheld_in_countries":[],"followed_by":null,"ext":{"highlightedLabel":{"r":{"ok":{}},"ttl":-1}},"require_some_consent":false}},{"in_reply_to_status_id_str":"995971048326610944","in_reply_to_status_id":995971048326610944,"supplemental_language":null,"created_at":"Mon May 14 10:28:45 +0000 2018","in_reply_to_user_id_str":"67300270","source":"<a href=\"http://twitter.com/download/iphone\" rel=\"nofollow\">Twitter for iPhone</a>","retweet_count":0,"retweeted":false,"geo":null,"in_reply_to_screen_name":"ucyucyucy","is_quote_status":false,"user_id_str":"14305560","full_text":"@ucyucyucy @StandUpIndo Betul. Termasuk.","conversation_id":995969407867342849,"id_str":"995974188421693440","in_reply_to_user_id":67300270,"favorite_count":0,"id":995974188421693440,"place":null,"lang":"in","quote_count":0,"conversation_id_str":"995969407867342849","favorited":false,"coordinates":null,"truncated":false,"reply_count":0,"crawler_target":{"resource_type":"social_media","stream_type":"account","specific_resource_type":"twitter","target_name":"332919636","extra_content":"Standupindo"},"entities":{"hashtags":[],"symbols":[],"user_mentions":[{"screen_name":"ucyucyucy","name":"Uchy Muharomi WSYDN","id":67300270,"id_str":"67300270","indices":[0,10]},{"screen_name":"Standupindo","name":"IG: standupindonesia","id":332919636,"id_str":"332919636","indices":[11,23]}],"urls":[]},"user_id":14305560,"display_text_range":[24,40],"contributors":null,"user":{"id":14305560,"id_str":"14305560","name":"Pandji Pragiwaksono","screen_name":"pandji","location":"Indonesia","description":"Stand-Up Comedian with 8 Special who is now running COMIKA, a company devoted to create the world a funnier place.","url":"https://t.co/SEa8vNPYbA","entities":{"url":{"urls":[{"url":"https://t.co/SEa8vNPYbA","expanded_url":"https://linktr.ee/pandji.pragiwaksono","display_url":"linktr.ee/pandji.pragiwa…","indices":[0,23]}]},"description":{"urls":[]}},"protected":false,"followers_count":1572888,"fast_followers_count":0,"normal_followers_count":1572888,"friends_count":346,"listed_count":1566,"created_at":"Fri Apr 04 19:35:56 +0000 2008","favourites_count":2230,"utc_offset":null,"time_zone":null,"geo_enabled":true,"verified":true,"statuses_count":270177,"media_count":24117,"lang":null,"contributors_enabled":false,"is_translator":false,"is_translation_enabled":false,"profile_background_color":"000000","profile_background_image_url":"http://abs.twimg.com/images/themes/theme1/bg.png","profile_background_image_url_https":"https://abs.twimg.com/images/themes/theme1/bg.png","profile_background_tile":false,"profile_image_url":"http://pbs.twimg.com/profile_images/1341056153468354574/kcfQnHeI_normal.jpg","profile_image_url_https":"https://pbs.twimg.com/profile_images/1341056153468354574/kcfQnHeI_normal.jpg","profile_banner_url":"https://pbs.twimg.com/profile_banners/14305560/1608097720","profile_image_extensions_alt_text":null,"profile_image_extensions_media_availability":null,"profile_image_extensions_media_color":{"palette":[{"rgb":{"red":177,"green":184,"blue":190},"percentage":40.08},{"rgb":{"red":39,"green":47,"blue":35},"percentage":32.09},{"rgb":{"red":115,"green":114,"blue":97},"percentage":10},{"rgb":{"red":14,"green":42,"blue":56},"percentage":6.72},{"rgb":{"red":68,"green":75,"blue":34},"percentage":5.21}]},"profile_image_extensions":{"mediaStats":{"r":{"missing":null},"ttl":-1}},"profile_banner_extensions_alt_text":null,"profile_banner_extensions_media_availability":null,"profile_banner_extensions_media_color":{"palette":[{"rgb":{"red":162,"green":161,"blue":162},"percentage":76.76},{"rgb":{"red":38,"green":45,"blue":51},"percentage":19.59},{"rgb":{"red":213,"green":190,"blue":175},"percentage":0.18},{"rgb":{"red":44,"green":40,"blue":26},"percentage":0.16}]},"profile_banner_extensions":{"mediaStats":{"r":{"missing":null},"ttl":-1}},"profile_link_color":"3CB904","profile_sidebar_border_color":"164700","profile_sidebar_fill_color":"255211","profile_text_color":"979595","profile_use_background_image":true,"has_extended_profile":true,"default_profile":false,"default_profile_image":false,"pinned_tweet_ids":[],"pinned_tweet_ids_str":[],"has_custom_timelines":true,"can_dm":null,"following":null,"follow_request_sent":null,"notifications":null,"muting":null,"blocking":null,"blocked_by":null,"want_retweets":null,"advertiser_account_type":"promotable_user","advertiser_account_service_levels":["analytics"],"business_profile_state":"none","translator_type":"regular","withheld_in_countries":[],"followed_by":null,"ext":{"highlightedLabel":{"r":{"ok":{}},"ttl":-1}},"require_some_consent":false}}]